pyeh/__init__.py
pyeh/main.py
pyeh-0.1.6.dist-info/LICENSE
pyeh-0.1.6.dist-info/METADATA
pyeh-0.1.6.dist-info/WHEEL
pyeh-0.1.6.dist-info/top_level.txt
pyeh-0.1.6.dist-info/RECORD
