Metadata-Version: 2.1
Name: pyeh
Version: 0.1.6
Summary: A small SDK for EH
Home-page: https://gitlab.com/konradp/pyeh
Author: Konrad P
License: UNKNOWN
Platform: UNKNOWN
Classifier: Programming Language :: Python :: 3
Classifier: License :: OSI Approved :: MIT License
Classifier: Operating System :: OS Independent
Requires-Dist: requests
